{
  "result": false,
  "model_name": "st1",
  "camera_exposer": 11100.0,
  "TemplateImagePath": "D:\\salcomp_project_v2\\ChargerVivo\\SalcompTwoCam\\Models\\st1\\FirstCam\\Template21_04_2022_18_42_38.bmp",
  "OriginalImagePath": "D:\\salcomp_project_v2\\ChargerVivo\\SalcompTwoCam\\Models\\st1\\FirstCam\\Original21_04_2022_18_42_38.bmp",
  "CheckTemplate": [],
  "CheckCheckEdges": [
    {
      "edgeRegion": {
        "point_x": 161,
        "point_y": 144,
        "imageWidth": 20,
        "imageHeight": 100,
        "template_image_path": "D:\\salcomp_project_v2\\ChargerVivo\\SalcompTwoCam\\Models\\st1\\FirstCam\\edgecheck21_04_2022_18_43_14.bmp"
      },
      "List": [
        {
          "nodeName": "AngleTolerance",
          "nodeRange": [
            1.0,
            128.0
          ],
          "nodeVal": 7.0
        },
        {
          "nodeName": "Angle",
          "nodeRange": [
            1.0,
            128.0
          ],
          "nodeVal": 58.0
        },
        {
          "nodeName": "EdgeThreshold",
          "nodeRange": [
            2.0,
            228.0
          ],
          "nodeVal": 32.0
        },
        {
          "nodeName": "Polarity",
          "nodeRange": [
            0.0,
            3.0
          ],
          "nodeVal": 1.0
        },
        {
          "nodeName": "Strength",
          "nodeRange": [
            0.0,
            2.0
          ],
          "nodeVal": 0.7
        }
      ],
      "angleTolerance": 7.0,
      "angle": 58.0,
      "threshold": 32.0,
      "distance": 0.0,
      "distanceTolerance": 0.0,
      "polarity": 1.0,
      "strength": 0.7,
      "direction": 0
    },
    {
      "edgeRegion": {
        "point_x": 161,
        "point_y": 144,
        "imageWidth": 20,
        "imageHeight": 100,
        "template_image_path": "D:\\salcomp_project_v2\\ChargerVivo\\SalcompTwoCam\\Models\\st1\\FirstCam\\edgecheck21_04_2022_18_43_14.bmp"
      },
      "List": [
        {
          "nodeName": "AngleTolerance",
          "nodeRange": [
            1.0,
            128.0
          ],
          "nodeVal": 7.0
        },
        {
          "nodeName": "Angle",
          "nodeRange": [
            1.0,
            128.0
          ],
          "nodeVal": 58.0
        },
        {
          "nodeName": "EdgeThreshold",
          "nodeRange": [
            2.0,
            228.0
          ],
          "nodeVal": 32.0
        },
        {
          "nodeName": "Polarity",
          "nodeRange": [
            0.0,
            3.0
          ],
          "nodeVal": 1.0
        },
        {
          "nodeName": "Strength",
          "nodeRange": [
            0.0,
            2.0
          ],
          "nodeVal": 0.0
        }
      ],
      "angleTolerance": 7.0,
      "angle": 58.0,
      "threshold": 32.0,
      "distance": 0.0,
      "distanceTolerance": 0.0,
      "polarity": 1.0,
      "strength": 0.0,
      "direction": 0
    }
  ],
  "TemplateCoordinate": {
    "point_x": 391,
    "point_y": 404,
    "imageWidth": 580,
    "imageHeight": 340,
    "template_image_path": "D:\\salcomp_project_v2\\ChargerVivo\\SalcompTwoCam\\Models\\st1\\FirstCam\\Template21_04_2022_18_42_38.bmp"
  }
}